{
  "folder": "S0WnjCTISsCU1zVZ",
  "name": "Arrow (Acid)",
  "type": "ammo",
  "img": "systems/cyberpunk-red-core/icons/compendium/ammo/bow_rubber.png",
  "system": {
    "description": {
      "value": "<p>Common ammunition often used as a cheap substitute for armor-piercing rounds. Each round contains a soft, reactive core designed to splatter on a target rather than penetrate it. Deals 1d6 damage less than basic ammunition of the same type, but always ablates the target's armor by the listed amount.</p>"
    },
    "source": {
      "book": "NC G&C",
      "page": 0
    },
    "favorite": false,
    "concealable": {
      "concealable": false,
      "isConcealed": false
    },
    "brand": "",
    "amount": 10,
    "price": {
      "market": 20
    },
    "variety": "arrow",
    "type": "special",
    "ablationValue": 2,
    "overrides": {
      "damage": {
        "mode": "set",
        "value": "3d6",
        "minimum": "1d6"
      },
      "autofire": {
        "mode": "none",
        "value": -1,
        "minimum": 3
      }
    },
    "installLocation": "mall",
    "size": 0
  },
  "effects": [],
  "flags": {
    "core": {},
    "cyberpunk-red-core": {
      "_migration": {
        "previous": "24",
        "current": 34
      }
    },
    "exportSource": {
      "world": "test",
      "system": "cyberpunk-red-core",
      "coreVersion": "12.343",
      "systemVersion": "v0.92.2"
    }
  },
  "_stats": {
    "coreVersion": "12.343",
    "systemId": "cyberpunk-red-core",
    "systemVersion": "v0.92.2",
    "createdTime": 1774385395850,
    "modifiedTime": 1774385395850,
    "lastModifiedBy": "bQcpWG6lypIQoS5d"
  }
}